griffe_typingdoc-0.3.0.dist-info/METADATA
griffe_typingdoc-0.3.0.dist-info/WHEEL
griffe_typingdoc-0.3.0.dist-info/entry_points.txt
griffe_typingdoc-0.3.0.dist-info/licenses/LICENSE
griffe_typingdoc/__init__.py
griffe_typingdoc/_internal/__init__.py
griffe_typingdoc/_internal/debug.py
griffe_typingdoc/_internal/docstrings.py
griffe_typingdoc/_internal/dynamic.py
griffe_typingdoc/_internal/extension.py
griffe_typingdoc/_internal/static.py
griffe_typingdoc/py.typed
griffe_typingdoc-0.3.0.dist-info/RECORD
