Metadata-Version: 2.4
Name: griffe-typingdoc
Version: 0.3.0
Summary: Griffe extension for PEP 727 – Documentation Metadata in Typing.
Author-Email: =?utf-8?q?Timoth=C3=A9e_Mazzucotelli?= <pawamoy@pm.me>
License-Expression: ISC
License-File: LICENSE
Classifier: Development Status :: 4 - Beta
Classifier: Intended Audience :: Developers
Classifier: Programming Language :: Python
Classifier: Programming Language :: Python :: 3
Classifier: Programming Language :: Python :: 3 :: Only
Classifier: Programming Language :: Python :: 3.9
Classifier: Programming Language :: Python :: 3.10
Classifier: Programming Language :: Python :: 3.11
Classifier: Programming Language :: Python :: 3.12
Classifier: Programming Language :: Python :: 3.13
Classifier: Programming Language :: Python :: 3.14
Classifier: Topic :: Documentation
Classifier: Topic :: Software Development
Classifier: Topic :: Software Development :: Documentation
Classifier: Topic :: Utilities
Classifier: Typing :: Typed
Project-URL: Homepage, https://mkdocstrings.github.io/griffe-typingdoc
Project-URL: Documentation, https://mkdocstrings.github.io/griffe-typingdoc
Project-URL: Changelog, https://mkdocstrings.github.io/griffe-typingdoc/changelog
Project-URL: Repository, https://github.com/mkdocstrings/griffe-typingdoc
Project-URL: Issues, https://github.com/mkdocstrings/griffe-typingdoc/issues
Project-URL: Discussions, https://github.com/mkdocstrings/griffe-typingdoc/discussions
Project-URL: Gitter, https://gitter.im/mkdocstrings/griffe-typingdoc
Project-URL: Funding, https://github.com/sponsors/pawamoy
Requires-Python: >=3.9
Requires-Dist: griffe>=1.14
Requires-Dist: typing-extensions>=4.7
